wordsegment/__init__.py
wordsegment/__main__.py
wordsegment/bigrams.txt
wordsegment/unigrams.txt
wordsegment/words.txt
wordsegment-1.3.0.dist-info/DESCRIPTION.rst
wordsegment-1.3.0.dist-info/METADATA
wordsegment-1.3.0.dist-info/RECORD
wordsegment-1.3.0.dist-info/WHEEL
wordsegment-1.3.0.dist-info/metadata.json
wordsegment-1.3.0.dist-info/top_level.txt
